llm_deep_research.py
llm_deep_research-0.0.2.dist-info/licenses/LICENSE
llm_deep_research-0.0.2.dist-info/METADATA
llm_deep_research-0.0.2.dist-info/WHEEL
llm_deep_research-0.0.2.dist-info/entry_points.txt
llm_deep_research-0.0.2.dist-info/top_level.txt
llm_deep_research-0.0.2.dist-info/RECORD
