Metadata-Version: 2.4
Name: llm-deep-research
Version: 0.0.2
Summary: LLM plugin of various deep research implementations
Author-email: nikkie <takuyafjp+develop@gmail.com>
License-Expression: Apache-2.0
Project-URL: Homepage, https://github.com/ftnext/llm-deep-research
Project-URL: Changelog, https://github.com/ftnext/llm-deep-research/releases
Project-URL: Issues, https://github.com/ftnext/llm-deep-research/issues
Project-URL: CI, https://github.com/ftnext/llm-deep-research/actions
Keywords: llm,deep research
Classifier: Development Status :: 1 - Planning
Classifier: Intended Audience :: Developers
Classifier: Intended Audience :: End Users/Desktop
Classifier: Intended Audience :: Science/Research
Classifier: Programming Language :: Python :: 3
Classifier: Programming Language :: Python :: 3.11
Classifier: Programming Language :: Python :: 3.12
Classifier: Programming Language :: Python :: 3.13
Classifier: Topic :: Scientific/Engineering :: Artificial Intelligence
Classifier: Topic :: Text Processing :: Linguistic
Classifier: Topic :: Utilities
Requires-Python: >=3.11
License-File: LICENSE
Requires-Dist: genai-processors>=1.0.5
Requires-Dist: llm
Requires-Dist: opentelemetry-instrumentation-google-genai>=0.3b0
Requires-Dist: opentelemetry-sdk>=1.35.0
Requires-Dist: pytest-asyncio[test]>=1.1.0
Provides-Extra: test
Requires-Dist: pytest; extra == "test"
Dynamic: license-file
